{"_ts":[1493627812],"_r":{"breakdown":{"html":{"bytes":[27316],"requests":[4]},"js":{"bytes":[803319],"requests":[22]},"css":{"bytes":[106320],"requests":[6]},"image":{"bytes":[8455777],"requests":[167]},"flash":{"bytes":[0],"requests":[0]},"font":{"bytes":[250457],"requests":[13]},"other":{"bytes":[4033293],"requests":[6]}},"date":[1493627812],"domElements":[2500],"domInteractive":[5120],"firstPaint":[2769],"fullyLoaded":[24468],"id":["170501_9P_F0V"],"loadTime":[17241],"render":[3603],"SpeedIndex":[5103],"TTFB":[414],"videoFrames":[[{"_i":"frame_0000.jpg","_t":0,"_vc":0},{"_i":"frame_0036.jpg","_t":3600,"_vc":70},{"_i":"frame_0039.jpg","_t":3900,"_vc":70},{"_i":"frame_0043.jpg","_t":4300,"_vc":70},{"_i":"frame_0057.jpg","_t":5700,"_vc":71},{"_i":"frame_0058.jpg","_t":5800,"_vc":72},{"_i":"frame_0060.jpg","_t":6000,"_vc":74},{"_i":"frame_0062.jpg","_t":6200,"_vc":74},{"_i":"frame_0065.jpg","_t":6500,"_vc":74},{"_i":"frame_0067.jpg","_t":6700,"_vc":74},{"_i":"frame_0078.jpg","_t":7800,"_vc":97},{"_i":"frame_0084.jpg","_t":8400,"_vc":96},{"_i":"frame_0087.jpg","_t":8700,"_vc":98},{"_i":"frame_0089.jpg","_t":8900,"_vc":98},{"_i":"frame_0121.jpg","_t":12100,"_vc":99},{"_i":"frame_0165.jpg","_t":16500,"_vc":99},{"_i":"frame_0183.jpg","_t":18300,"_vc":98},{"_i":"frame_0184.jpg","_t":18400,"_vc":98},{"_i":"frame_0186.jpg","_t":18600,"_vc":98},{"_i":"frame_0188.jpg","_t":18800,"_vc":99},{"_i":"frame_0190.jpg","_t":19000,"_vc":99},{"_i":"frame_0192.jpg","_t":19200,"_vc":99},{"_i":"frame_0199.jpg","_t":19900,"_vc":99},{"_i":"frame_0201.jpg","_t":20100,"_vc":99},{"_i":"frame_0203.jpg","_t":20300,"_vc":99},{"_i":"frame_0204.jpg","_t":20400,"_vc":99},{"_i":"frame_0206.jpg","_t":20600,"_vc":99},{"_i":"frame_0207.jpg","_t":20700,"_vc":99},{"_i":"frame_0209.jpg","_t":20900,"_vc":99},{"_i":"frame_0210.jpg","_t":21000,"_vc":99},{"_i":"frame_0212.jpg","_t":21200,"_vc":99},{"_i":"frame_0233.jpg","_t":23300,"_vc":98},{"_i":"frame_0235.jpg","_t":23500,"_vc":97},{"_i":"frame_0237.jpg","_t":23700,"_vc":97},{"_i":"frame_0239.jpg","_t":23900,"_vc":97},{"_i":"frame_0241.jpg","_t":24100,"_vc":97},{"_i":"frame_0243.jpg","_t":24300,"_vc":97},{"_i":"frame_0251.jpg","_t":25100,"_vc":98},{"_i":"frame_0253.jpg","_t":25300,"_vc":98},{"_i":"frame_0254.jpg","_t":25400,"_vc":98},{"_i":"frame_0256.jpg","_t":25600,"_vc":98},{"_i":"frame_0257.jpg","_t":25700,"_vc":97},{"_i":"frame_0259.jpg","_t":25900,"_vc":98},{"_i":"frame_0261.jpg","_t":26100,"_vc":98},{"_i":"frame_0269.jpg","_t":26900,"_vc":98},{"_i":"frame_0271.jpg","_t":27100,"_vc":99},{"_i":"frame_0273.jpg","_t":27300,"_vc":99},{"_i":"frame_0274.jpg","_t":27400,"_vc":99},{"_i":"frame_0275.jpg","_t":27500,"_vc":98},{"_i":"frame_0277.jpg","_t":27700,"_vc":99},{"_i":"frame_0279.jpg","_t":27900,"_vc":99},{"_i":"frame_0280.jpg","_t":28000,"_vc":100}]],"visualComplete":[28000],"lighthouse":[null],"pagespeed":[33]}}